{
  "CF101985701": {
    "contest_id": 1465,
    "language": "GNU C++14",
    "path": "codeforces/1465/A.cpp",
    "problem_index": "A",
    "problem_name": "In-game Chat",
    "problem_url": "https://codeforces.com/contest/1465/problem/A",
    "submission_id": "CF101985701",
    "submission_url": "https://codeforces.com/contest/1465/submission/101985701",
    "tags": [
      "implementation"
    ],
    "timestamp": "Dec/21/2020 23:41"
  },
  "CF101986877": {
    "contest_id": 1465,
    "language": "GNU C++14",
    "path": "codeforces/1465/B.cpp",
    "problem_index": "B",
    "problem_name": "Fair Numbers",
    "problem_url": "https://codeforces.com/contest/1465/problem/B",
    "submission_id": "CF101986877",
    "submission_url": "https://codeforces.com/contest/1465/submission/101986877",
    "tags": [
      "brute force",
      "number theory"
    ],
    "timestamp": "Dec/21/2020 23:58"
  }
}